{"is_employee": false, "reputation_change_quarter": 84, "user_id": 1092632, "account_id": 1099997, "location": "Berlin, Germany", "website_url": "http://www.idesignz.de", "reputation_change_month": 0, "last_modified_date": 1475305175, "profile_image": "https://www.gravatar.com/avatar/c690fdeefbe626c49bdd3f00f8e59acc?s=128&d=identicon&r=PG", "user_type": "registered", "creation_date": 1323631812, "last_access_date": 1477934172, "reputation": 590, "link": "http://stackoverflow.com/users/1092632/primus", "reputation_change_week": 0, "accept_rate": 70, "display_name": "PrimuS", "badge_counts": {"gold": 1, "silver": 5, "bronze": 18}, "reputation_change_year": 272, "reputation_change_day": 0}