{"is_employee": false, "reputation_change_quarter": 16, "user_id": 1268719, "account_id": 1323384, "location": "London, United Kingdom", "website_url": "http://www.jordan-dimov.com/", "reputation_change_month": 0, "age": 35, "last_modified_date": 1438505020, "profile_image": "https://www.gravatar.com/avatar/c3a516958b632befd68278ccf3de1b25?s=128&d=identicon&r=PG", "user_type": "registered", "creation_date": 1331720727, "last_access_date": 1477932063, "reputation": 646, "link": "http://stackoverflow.com/users/1268719/jordan-dimov", "reputation_change_week": -1, "accept_rate": 29, "display_name": "Jordan Dimov", "badge_counts": {"gold": 0, "silver": 5, "bronze": 14}, "reputation_change_year": 112, "reputation_change_day": 0}