{"is_employee": false, "reputation_change_quarter": 14, "user_id": 1460166, "account_id": 1572874, "website_url": "", "reputation_change_month": 0, "last_modified_date": 1467173646, "profile_image": "https://www.gravatar.com/avatar/4d53fb127853d2c7af6f39cbedbf9b96?s=128&d=identicon&r=PG", "user_type": "registered", "creation_date": 1339821802, "last_access_date": 1477969547, "reputation": 1238, "link": "http://stackoverflow.com/users/1460166/tak", "reputation_change_week": 0, "accept_rate": 92, "display_name": "Tak", "badge_counts": {"gold": 3, "silver": 18, "bronze": 47}, "reputation_change_year": 160, "reputation_change_day": 0}