{"is_employee": false, "reputation_change_quarter": 0, "user_id": 1902489, "account_id": 2144571, "location": "London, United Kingdom", "website_url": "http://crowdclassics.co.uk", "reputation_change_month": 0, "age": 29, "last_modified_date": 1461348300, "profile_image": "https://i.stack.imgur.com/8CYve.jpg?s=128&g=1", "user_type": "registered", "creation_date": 1355437768, "last_access_date": 1477925697, "reputation": 6, "link": "http://stackoverflow.com/users/1902489/ireallycare", "reputation_change_week": 0, "display_name": "ireallycare", "badge_counts": {"gold": 0, "silver": 0, "bronze": 3}, "reputation_change_year": 0, "reputation_change_day": 0}