{"is_employee": false, "reputation_change_quarter": 7, "user_id": 271526, "account_id": 100798, "website_url": "", "reputation_change_month": 0, "last_modified_date": 1475085423, "profile_image": "https://www.gravatar.com/avatar/59debb0f1e43f6773cb6a655ea3516ce?s=128&d=identicon&r=PG", "user_type": "registered", "creation_date": 1265939076, "last_access_date": 1477876455, "reputation": 132, "link": "http://stackoverflow.com/users/271526/gabe", "reputation_change_week": 0, "accept_rate": 67, "display_name": "Gabe", "badge_counts": {"gold": 0, "silver": 3, "bronze": 12}, "reputation_change_year": 17, "reputation_change_day": 0}