{"is_employee": false, "reputation_change_quarter": 2, "user_id": 3055219, "account_id": 3667098, "website_url": "", "reputation_change_month": 0, "last_modified_date": 1469890545, "profile_image": "https://i.stack.imgur.com/WsJZ8.jpg?s=128&g=1", "user_type": "registered", "creation_date": 1385927611, "last_access_date": 1477931595, "reputation": 879, "link": "http://stackoverflow.com/users/3055219/toaster", "reputation_change_week": 0, "accept_rate": 100, "display_name": "Toaster", "badge_counts": {"gold": 0, "silver": 5, "bronze": 18}, "reputation_change_year": 369, "reputation_change_day": 0}