{"is_employee": false, "reputation_change_quarter": 3, "user_id": 4061326, "account_id": 5059062, "location": "Polska", "website_url": "https://pl.linkedin.com/in/piotrtynecki", "reputation_change_month": 0, "last_modified_date": 1477437475, "profile_image": "https://i.stack.imgur.com/w37qa.jpg?s=128&g=1", "user_type": "registered", "creation_date": 1411220870, "last_access_date": 1477931734, "reputation": 4, "link": "http://stackoverflow.com/users/4061326/katharsis", "reputation_change_week": 0, "display_name": "Katharsis", "badge_counts": {"gold": 0, "silver": 0, "bronze": 2}, "reputation_change_year": 3, "reputation_change_day": 0}