{"is_employee": false, "reputation_change_quarter": 5, "user_id": 4274747, "account_id": 5364334, "website_url": "", "reputation_change_month": 0, "last_modified_date": 1460201804, "profile_image": "https://www.gravatar.com/avatar/b4606ccdd2a9e3d8f6abc88a7db44fad?s=128&d=identicon&r=PG&f=1", "user_type": "registered", "creation_date": 1416492907, "last_access_date": 1477517550, "reputation": 37, "link": "http://stackoverflow.com/users/4274747/vm1", "reputation_change_week": 0, "accept_rate": 80, "display_name": "VM1", "badge_counts": {"gold": 0, "silver": 0, "bronze": 6}, "reputation_change_year": 10, "reputation_change_day": 0}