{"is_employee": false, "reputation_change_quarter": 33, "user_id": 4589550, "account_id": 5821689, "reputation_change_month": 0, "last_modified_date": 1476497136, "profile_image": "https://www.gravatar.com/avatar/a46c412f2c2942a3a8210b0e8091cc1a?s=128&d=identicon&r=PG&f=1", "user_type": "registered", "creation_date": 1424463262, "last_access_date": 1477942191, "reputation": 722, "link": "http://stackoverflow.com/users/4589550/stefano-potter", "reputation_change_week": 0, "accept_rate": 87, "display_name": "Stefano Potter", "badge_counts": {"gold": 0, "silver": 2, "bronze": 13}, "reputation_change_year": 342, "reputation_change_day": 0}