{"is_employee": false, "reputation_change_quarter": 4, "user_id": 6733153, "account_id": 9037970, "reputation_change_month": 0, "last_modified_date": 1474698532, "profile_image": "https://www.gravatar.com/avatar/64695679246992dbd668a2b4cd46f01e?s=128&d=identicon&r=PG&f=1", "user_type": "registered", "creation_date": 1471577112, "last_access_date": 1477658747, "reputation": 5, "link": "http://stackoverflow.com/users/6733153/zorgan", "reputation_change_week": 0, "display_name": "Zorgan", "badge_counts": {"gold": 0, "silver": 0, "bronze": 2}, "reputation_change_year": 4, "reputation_change_day": 0}