{"Plot": "A veteran hostage negotiator's next call leads him to an overrun insane asylum. He soon finds that dark forces are pushing the patients to commit atrocities, and he may be the only one that can stop them.", "Rated": "R", "Response": "True", "Language": "English", "Title": "Asylum", "Country": "USA", "Writer": "Chris Mancini (Comedy Screenplay), Chris Mancini (Horror Screenplay), Tex Wall (horror screenplay)", "Metascore": "N/A", "imdbRating": "2.7", "Director": "Todor Chapkanov", "Released": "02 Jun 2015", "Actors": "Stephen Rea, Bruce Payne, Dimo Alexiev, Velizar Binev", "Year": "2014", "Genre": "Horror", "Awards": "N/A", "Runtime": "93 min", "Type": "movie", "Poster": "http://ia.media-imdb.com/images/M/MV5BMTA0Mjk3NDcxMzdeQTJeQWpwZ15BbWU3MDY1OTg3Njg@._V1_SX300.jpg", "imdbVotes": "260", "imdbID": "tt2259858"}