{"Plot": "A young girl struggles to overcome her fears in order to find her voice and happiness in this touching story of staying true to ones hopes and dreams.", "Rated": "N/A", "Response": "True", "Language": "English", "Title": "Zoey's Hill", "Country": "Canada", "Writer": "Elaine Mah, Jorge Molina (story), Jorge Molina", "Metascore": "N/A", "imdbRating": "N/A", "Director": "Jorge Molina", "Released": "03 May 2013", "Actors": "Elaine Mah, Eve Molina, Nicolas Molina", "Year": "2013", "Genre": "Short, Drama, Family", "Awards": "N/A", "Runtime": "10 min", "Type": "movie", "Poster": "N/A", "imdbVotes": "N/A", "imdbID": "tt2621734"}