{"totalSeasons": "5", "Plot": "Funny skits and more. Based on the hit YouTube channel \"AwesomenessTV\".", "Rated": "N/A", "Response": "True", "Language": "English", "Title": "AwesomenessTV", "Country": "USA", "Writer": "Brian Robbins", "Metascore": "N/A", "imdbRating": "3.1", "Director": "N/A", "Released": "01 Jul 2013", "Actors": "Isaiah Fredericks, Josiah Fredericks, Lia Marie Johnson, Meghan Rienks", "Year": "2013\u2013", "Genre": "Comedy", "Awards": "N/A", "Runtime": "30 min", "Type": "series", "Poster": "http://ia.media-imdb.com/images/M/MV5BMTU2OTU1ODAxOF5BMl5BanBnXkFtZTgwMjc5NTcwNDE@._V1_SX300.jpg", "imdbVotes": "223", "imdbID": "tt3100634"}