{"Plot": "When Christine, a single woman, decides to move, she enlists the help from some local day laborers. All seems to be going well, until she leaves to get Tacos For Lunch. She returns to a ...", "Rated": "N/A", "Response": "True", "Language": "English", "Title": "Tacos for Lunch", "Country": "USA", "Writer": "Chandan Gupta (story), Chandan Gupta", "Metascore": "N/A", "imdbRating": "N/A", "Director": "Chandan Gupta", "Released": "N/A", "Actors": "Billynaire Cruz, Therese McLaughlin", "Year": "2013", "Genre": "Short, Action, Drama", "Awards": "N/A", "Runtime": "26 min", "Type": "movie", "Poster": "N/A", "imdbVotes": "N/A", "imdbID": "tt3341144"}