{"totalSeasons": "1", "Plot": "A livestreamed digital series co-produced by Big Vision Creative and ABC News, featuring conversations with visionaries in entertainment about the innovative ways they are creating their work and delivering it to the public.", "Rated": "N/A", "Response": "True", "Language": "English", "Title": "Big Vision Creatives Powered by ABC News", "Country": "USA", "Writer": "N/A", "Metascore": "N/A", "imdbRating": "N/A", "Director": "N/A", "Released": "01 Oct 2014", "Actors": "Adrian Grenier, Joe Manganiello, Alex Cirillo, Dani Faith Leonard", "Year": "2014\u2013", "Genre": "News", "Awards": "N/A", "Runtime": "N/A", "Type": "series", "Poster": "N/A", "imdbVotes": "N/A", "imdbID": "tt4644396"}