{"Plot": "A short documentary that explores the work of dancer/choreographers Eiko & Koma as they begin a multi-year Retrospective Project. The two artists speak about their intended impact on ...", "Rated": "N/A", "Response": "True", "Language": "English", "Title": "Eiko & Koma: The Retrospective Project", "Country": "USA", "Writer": "N/A", "Metascore": "N/A", "imdbRating": "N/A", "Director": "Joanna Arnow", "Released": "N/A", "Actors": "N/A", "Year": "2010", "Genre": "Documentary, Short, Biography", "Awards": "N/A", "Runtime": "10 min", "Type": "movie", "Poster": "N/A", "imdbVotes": "N/A", "imdbID": "tt1639386"}