{"Plot": "Patricia's obsession with finishing her first novel brings her to the edge when her lead character, Boris, manifests into her world. And once he does, writers block intervenes.", "Rated": "N/A", "Response": "True", "Language": "English", "Title": "Patricia", "Country": "N/A", "Writer": "Cameron Miller-Desart", "Metascore": "N/A", "imdbRating": "N/A", "Director": "Cameron Miller-Desart", "Released": "09 Jan 2015", "Actors": "Emih Abrahamson, Drew Ernhout, John von Nolde II, Philip Bushell", "Year": "2015", "Genre": "Short", "Awards": "N/A", "Runtime": "N/A", "Type": "movie", "Poster": "N/A", "imdbVotes": "N/A", "imdbID": "tt4325894"}