{"Plot": "A high school in desolate, Barrow, Alaska finds new hope and purpose for the isolated Native Eskimo kids through a controversial football program and an unlikely partner in a Florida football mom.", "Rated": "N/A", "Response": "True", "Language": "N/A", "Title": "Touchdown on the Tundra", "Country": "USA", "Writer": "Torry Martin, Marshal Younger", "Metascore": "N/A", "imdbRating": "N/A", "Director": "N/A", "Released": "N/A", "Actors": "N/A", "Year": "2016", "Genre": "Drama", "Awards": "N/A", "Runtime": "N/A", "Type": "movie", "Poster": "N/A", "imdbVotes": "N/A", "imdbID": "tt4527604"}