{"Plot": "Let Them Eat Cake is about an American missionary in war-torn Iraq who believes he relates to the experience of an Iraqi Christian. He is surprised to find the Iraqi man afraid to come to America because of what he's heard on cable news.", "Rated": "N/A", "Response": "True", "Language": "English", "Title": "Let Them Eat Cake", "Country": "USA", "Writer": "Mark Overholt", "Metascore": "N/A", "imdbRating": "N/A", "Director": "Mark Overholt", "Released": "22 Nov 2015", "Actors": "Mark Overholt, Ali Saam", "Year": "2015", "Genre": "Short, Comedy", "Awards": "N/A", "Runtime": "N/A", "Type": "movie", "Poster": "http://ia.media-imdb.com/images/M/MV5BMTU3NzU5ODk3N15BMl5BanBnXkFtZTgwNzM2ODg0NzE@._V1_SX300.jpg", "imdbVotes": "N/A", "imdbID": "tt5244254"}