{"totalSeasons": "N/A", "Plot": "The 12 Steps to Multimedia Success is a coaching program for brand owners and content creators. We coach brand owners and small businesses on the latest techniques in audio, video and print...", "Rated": "N/A", "Response": "True", "Language": "English", "Title": "12 Steps to Multimedia Success", "Country": "USA", "Writer": "Mareo-Ahmir Lawson", "Metascore": "N/A", "imdbRating": "9.4", "Director": "N/A", "Released": "10 Jul 2016", "Actors": "Richard Bamuhaira, Mareo-Ahmir Lawson, Edreick Stitts, Taylor Thibodaux", "Year": "2016\u2013", "Genre": "Talk-Show", "Awards": "N/A", "Runtime": "50 min", "Type": "series", "Poster": "https://images-na.ssl-images-amazon.com/images/M/MV5BYWZlNDY4NjYtZjA2Yi00Mzg1LThhYzQtMGRhY2M4NmNkNjdkXkEyXkFqcGdeQXVyMzI3NjI4Mg@@._V1_SX300.jpg", "imdbVotes": "9", "imdbID": "tt6054362"}