{"contributors": null, "truncated": false, "text": "After a hectic working weekend - we replenish the body whiles watching #FastFive \ud83d\ude4c\ud83c\udffe\ud83d\ude4c\ud83c\udffe\ud83d\ude4c\ud83c\udffe https://t.co/QY0yUxf8Hz", "is_quote_status": false, "in_reply_to_status_id": null, "id": 805490882245955585, "favorite_count": 0, "entities": {"symbols": [], "user_mentions": [], "hashtags": [{"indices": [71, 80], "text": "FastFive"}], "urls": [{"url": "https://t.co/QY0yUxf8Hz", "indices": [88, 111], "expanded_url": "https://www.instagram.com/p/BNm0tT8DDgr/", "display_url": "instagram.com/p/BNm0tT8DDgr/"}]}, "retweeted": false, "coordinates": null, "source": "<a href=\"http://instagram.com\" rel=\"nofollow\">Instagram</a>", "in_reply_to_screen_name": null, "in_reply_to_user_id": null, "retweet_count": 0, "id_str": "805490882245955585", "favorited": false, "user": {"follow_request_sent": false, "has_extended_profile": false, "profile_use_background_image": true, "default_profile_image": false, "id": 39990228, "profile_background_image_url_https": "https://abs.twimg.com/images/themes/theme1/bg.png", "verified": false, "translator_type": "none", "profile_text_color": "333333", "profile_image_url_https": "https://pbs.twimg.com/profile_images/672112973733830656/doA1kmQK_normal.png", "profile_sidebar_fill_color": "DDEEF6", "entities": {"description": {"urls": []}}, "followers_count": 302, "profile_sidebar_border_color": "C0DEED", "id_str": "39990228", "profile_background_color": "C0DEED", "listed_count": 4, "is_translation_enabled": false, "utc_offset": -10800, "statuses_count": 5466, "description": "KAIzen- impossible is nothing", "friends_count": 175, "location": "\u00dcT: -26.026194,28.065176", "profile_link_color": "1DA1F2", "profile_image_url": "http://pbs.twimg.com/profile_images/672112973733830656/doA1kmQK_normal.png", "following": false, "geo_enabled": true, "profile_background_image_url": "http://abs.twimg.com/images/themes/theme1/bg.png", "screen_name": "zosuliwe", "lang": "en", "profile_background_tile": false, "favourites_count": 19, "name": "Zos_kay1", "notifications": false, "url": null, "created_at": "Thu May 14 13:15:10 +0000 2009", "contributors_enabled": false, "time_zone": "Greenland", "protected": false, "default_profile": true, "is_translator": false}, "geo": null, "in_reply_to_user_id_str": null, "possibly_sensitive": false, "lang": "en", "created_at": "Sun Dec 04 19:16:06 +0000 2016", "in_reply_to_status_id_str": null, "place": null, "metadata": {"iso_language_code": "en", "result_type": "recent"}}