{"contributors": null, "truncated": false, "text": "Action League White Lantern Sinestro vs #GreenLantern New in Package https://t.co/e6Rg5ssMnb #eBay #Auction https://t.co/QfYREQZFAf", "is_quote_status": false, "in_reply_to_status_id": null, "id": 805648934106341376, "favorite_count": 0, "entities": {"symbols": [], "user_mentions": [], "hashtags": [{"indices": [40, 53], "text": "GreenLantern"}, {"indices": [93, 98], "text": "eBay"}, {"indices": [99, 107], "text": "Auction"}], "urls": [{"url": "https://t.co/e6Rg5ssMnb", "indices": [69, 92], "expanded_url": "http://dlvr.it/MpfttF", "display_url": "dlvr.it/MpfttF"}], "media": [{"expanded_url": "https://twitter.com/BlakeLively_See/status/805648934106341376/photo/1", "display_url": "pic.twitter.com/QfYREQZFAf", "url": "https://t.co/QfYREQZFAf", "media_url_https": "https://pbs.twimg.com/media/Cy49bxRUcAANMQ3.jpg", "id_str": "805648930637639680", "sizes": {"small": {"h": 400, "resize": "fit", "w": 400}, "large": {"h": 400, "resize": "fit", "w": 400}, "medium": {"h": 400, "resize": "fit", "w": 400}, "thumb": {"h": 150, "resize": "crop", "w": 150}}, "indices": [108, 131], "type": "photo", "id": 805648930637639680, "media_url": "http://pbs.twimg.com/media/Cy49bxRUcAANMQ3.jpg"}]}, "retweeted": false, "coordinates": null, "source": "<a href=\"http://dlvr.it\" rel=\"nofollow\">dlvr.it</a>", "in_reply_to_screen_name": null, "in_reply_to_user_id": null, "retweet_count": 0, "id_str": "805648934106341376", "favorited": false, "user": {"follow_request_sent": false, "has_extended_profile": false, "profile_use_background_image": true, "default_profile_image": false, "id": 783747823, "profile_background_image_url_https": "https://abs.twimg.com/images/themes/theme10/bg.gif", "verified": false, "translator_type": "none", "profile_text_color": "333333", "profile_image_url_https": "https://pbs.twimg.com/profile_images/2547637751/2mkf73svkjcyxuec644p_normal.jpeg", "profile_sidebar_fill_color": "DDEEF6", "entities": {"description": {"urls": []}}, "followers_count": 1954, "profile_sidebar_border_color": "C0DEED", "id_str": "783747823", "profile_background_color": "642D8B", "listed_count": 406, "is_translation_enabled": false, "utc_offset": -28800, "statuses_count": 258650, "description": "The latest #BlakeLively #Gossip online keeping you up to date with all Blake Lively news. #CelebrityNews", "friends_count": 232, "location": "", "profile_link_color": "0084B4", "profile_image_url": "http://pbs.twimg.com/profile_images/2547637751/2mkf73svkjcyxuec644p_normal.jpeg", "following": false, "geo_enabled": false, "profile_background_image_url": "http://abs.twimg.com/images/themes/theme10/bg.gif", "screen_name": "BlakeLively_See", "lang": "en", "profile_background_tile": true, "favourites_count": 0, "name": "Blake Lively Watch", "notifications": false, "url": null, "created_at": "Mon Aug 27 03:47:23 +0000 2012", "contributors_enabled": false, "time_zone": "Pacific Time (US & Canada)", "protected": false, "default_profile": false, "is_translator": false}, "geo": null, "in_reply_to_user_id_str": null, "possibly_sensitive": false, "lang": "en", "created_at": "Mon Dec 05 05:44:08 +0000 2016", "in_reply_to_status_id_str": null, "place": null, "extended_entities": {"media": [{"expanded_url": "https://twitter.com/BlakeLively_See/status/805648934106341376/photo/1", "display_url": "pic.twitter.com/QfYREQZFAf", "url": "https://t.co/QfYREQZFAf", "media_url_https": "https://pbs.twimg.com/media/Cy49bxRUcAANMQ3.jpg", "id_str": "805648930637639680", "sizes": {"small": {"h": 400, "resize": "fit", "w": 400}, "large": {"h": 400, "resize": "fit", "w": 400}, "medium": {"h": 400, "resize": "fit", "w": 400}, "thumb": {"h": 150, "resize": "crop", "w": 150}}, "indices": [108, 131], "type": "photo", "id": 805648930637639680, "media_url": "http://pbs.twimg.com/media/Cy49bxRUcAANMQ3.jpg"}]}, "metadata": {"iso_language_code": "en", "result_type": "recent"}}