{"contributors": null, "truncated": false, "text": "RT @DJChop47: Revisiting the #ElectionYear2016 #ThePurge #QuickSketch #FanArt #Masks #ThePurgeElectionYear #HorrorMovie #Art #Drawing #Libe\u2026", "is_quote_status": false, "in_reply_to_status_id": null, "id": 806496320466862080, "favorite_count": 0, "entities": {"symbols": [], "user_mentions": [{"id": 619363041, "indices": [3, 12], "id_str": "619363041", "screen_name": "DJChop47", "name": "Daniel E Barnard Jr"}], "hashtags": [{"indices": [29, 46], "text": "ElectionYear2016"}, {"indices": [47, 56], "text": "ThePurge"}, {"indices": [57, 69], "text": "QuickSketch"}, {"indices": [70, 77], "text": "FanArt"}, {"indices": [78, 84], "text": "Masks"}, {"indices": [85, 106], "text": "ThePurgeElectionYear"}, {"indices": [107, 119], "text": "HorrorMovie"}, {"indices": [120, 124], "text": "Art"}, {"indices": [125, 133], "text": "Drawing"}], "urls": []}, "retweeted": false, "coordinates": null, "source": "<a href=\"http://twitter.com/download/iphone\" rel=\"nofollow\">Twitter for iPhone</a>", "in_reply_to_screen_name": null, "in_reply_to_user_id": null, "retweet_count": 1, "id_str": "806496320466862080", "favorited": false, "retweeted_status": {"contributors": null, "truncated": true, "text": "Revisiting the #ElectionYear2016 #ThePurge #QuickSketch #FanArt #Masks #ThePurgeElectionYear #HorrorMovie #Art\u2026 https://t.co/nzMUYEBZtQ", "is_quote_status": false, "in_reply_to_status_id": null, "id": 802628139109249024, "favorite_count": 3, "entities": {"symbols": [], "user_mentions": [], "hashtags": [{"indices": [15, 32], "text": "ElectionYear2016"}, {"indices": [33, 42], "text": "ThePurge"}, {"indices": [43, 55], "text": "QuickSketch"}, {"indices": [56, 63], "text": "FanArt"}, {"indices": [64, 70], "text": "Masks"}, {"indices": [71, 92], "text": "ThePurgeElectionYear"}, {"indices": [93, 105], "text": "HorrorMovie"}, {"indices": [106, 110], "text": "Art"}], "urls": [{"url": "https://t.co/nzMUYEBZtQ", "indices": [112, 135], "expanded_url": "https://twitter.com/i/web/status/802628139109249024", "display_url": "twitter.com/i/web/status/8\u2026"}]}, "retweeted": false, "coordinates": null, "source": "<a href=\"http://twitter.com/download/iphone\" rel=\"nofollow\">Twitter for iPhone</a>", "in_reply_to_screen_name": null, "in_reply_to_user_id": null, "retweet_count": 1, "id_str": "802628139109249024", "favorited": false, "user": {"follow_request_sent": false, "has_extended_profile": false, "profile_use_background_image": true, "default_profile_image": false, "id": 619363041, "profile_background_image_url_https": "https://pbs.twimg.com/profile_background_images/439619761161261057/p7084otH.jpeg", "verified": false, "translator_type": "none", "profile_text_color": "333333", "profile_image_url_https": "https://pbs.twimg.com/profile_images/801561225553477632/oTJ8bnU2_normal.jpg", "profile_sidebar_fill_color": "DDEEF6", "entities": {"url": {"urls": [{"url": "https://t.co/v0L8PUlxbD", "indices": [0, 23], "expanded_url": "http://djchop47.tumblr.com/", "display_url": "djchop47.tumblr.com"}]}, "description": {"urls": [{"url": "https://t.co/RQY85NbqL1", "indices": [121, 144], "expanded_url": "http://chop47.tumblr.com/", "display_url": "chop47.tumblr.com"}]}}, "followers_count": 74, "profile_sidebar_border_color": "FFFFFF", "id_str": "619363041", "profile_background_color": "C0DEED", "listed_count": 15, "is_translation_enabled": false, "utc_offset": null, "statuses_count": 497, "description": "Wanna be friends with an artist? #ThatGuyYouKnowTheOne #BrownEyedBoyMagic                                                https://t.co/RQY85NbqL1", "friends_count": 172, "location": "", "profile_link_color": "1783BD", "profile_image_url": "http://pbs.twimg.com/profile_images/801561225553477632/oTJ8bnU2_normal.jpg", "following": false, "geo_enabled": false, "profile_banner_url": "https://pbs.twimg.com/profile_banners/619363041/1480893328", "profile_background_image_url": "http://pbs.twimg.com/profile_background_images/439619761161261057/p7084otH.jpeg", "screen_name": "DJChop47", "lang": "en", "profile_background_tile": true, "favourites_count": 1861, "name": "Daniel E Barnard Jr", "notifications": false, "url": "https://t.co/v0L8PUlxbD", "created_at": "Tue Jun 26 17:50:54 +0000 2012", "contributors_enabled": false, "time_zone": null, "protected": false, "default_profile": false, "is_translator": false}, "geo": null, "in_reply_to_user_id_str": null, "possibly_sensitive": false, "lang": "en", "created_at": "Sat Nov 26 21:40:35 +0000 2016", "in_reply_to_status_id_str": null, "place": null, "metadata": {"iso_language_code": "en", "result_type": "recent"}}, "user": {"follow_request_sent": false, "has_extended_profile": false, "profile_use_background_image": true, "default_profile_image": false, "id": 128587455, "profile_background_image_url_https": "https://pbs.twimg.com/profile_background_images/803516080/94738e56387d0e79ed64eba9c5b7800a.jpeg", "verified": false, "translator_type": "none", "profile_text_color": "302925", "profile_image_url_https": "https://pbs.twimg.com/profile_images/1822605743/l_normal.jpg", "profile_sidebar_fill_color": "543012", "entities": {"url": {"urls": [{"url": "http://t.co/odzILDlKMq", "indices": [0, 22], "expanded_url": "http://www.crawlordietrilogy.com", "display_url": "crawlordietrilogy.com"}]}, "description": {"urls": []}}, "followers_count": 15987, "profile_sidebar_border_color": "000000", "id_str": "128587455", "profile_background_color": "FFFFFF", "listed_count": 673, "is_translation_enabled": false, "utc_offset": null, "statuses_count": 65945, "description": "We \u2665 HORROR FANS/WEBSITES/FILMS/FILMMAKERS! IN love with movies and the THRILLER/HORROR movie CRAWL or DIE!", "friends_count": 8655, "location": "Los Angeles, CA", "profile_link_color": "0A0A09", "profile_image_url": "http://pbs.twimg.com/profile_images/1822605743/l_normal.jpg", "following": false, "geo_enabled": true, "profile_banner_url": "https://pbs.twimg.com/profile_banners/128587455/1444095653", "profile_background_image_url": "http://pbs.twimg.com/profile_background_images/803516080/94738e56387d0e79ed64eba9c5b7800a.jpeg", "screen_name": "EXTREMEINDIE", "lang": "en", "profile_background_tile": false, "favourites_count": 18395, "name": "Hardcore Horror Fan", "notifications": false, "url": "http://t.co/odzILDlKMq", "created_at": "Thu Apr 01 15:28:25 +0000 2010", "contributors_enabled": false, "time_zone": null, "protected": false, "default_profile": false, "is_translator": false}, "geo": null, "in_reply_to_user_id_str": null, "lang": "en", "created_at": "Wed Dec 07 13:51:21 +0000 2016", "in_reply_to_status_id_str": null, "place": null, "metadata": {"iso_language_code": "en", "result_type": "recent"}}