{"contributors": null, "truncated": false, "text": "RT @JackPosobiec: Buried deep down this WaPo Secret CIA assessment article they admit they have zero evidence https://t.co/ppaNgmXX9X", "is_quote_status": false, "in_reply_to_status_id": null, "id": 807448196960161792, "favorite_count": 0, "entities": {"symbols": [], "user_mentions": [{"id": 592730371, "indices": [3, 16], "id_str": "592730371", "screen_name": "JackPosobiec", "name": "Jack Posobiec"}], "hashtags": [], "urls": [], "media": [{"source_user_id": 592730371, "source_status_id_str": "807393274558369792", "expanded_url": "https://twitter.com/JackPosobiec/status/807393274558369792/photo/1", "display_url": "pic.twitter.com/ppaNgmXX9X", "url": "https://t.co/ppaNgmXX9X", "media_url_https": "https://pbs.twimg.com/media/CzRv5OFXcAILC2h.jpg", "source_user_id_str": "592730371", "source_status_id": 807393274558369792, "id_str": "807393262029991938", "sizes": {"small": {"h": 199, "resize": "fit", "w": 680}, "large": {"h": 219, "resize": "fit", "w": 750}, "medium": {"h": 219, "resize": "fit", "w": 750}, "thumb": {"h": 150, "resize": "crop", "w": 150}}, "indices": [110, 133], "type": "photo", "id": 807393262029991938, "media_url": "http://pbs.twimg.com/media/CzRv5OFXcAILC2h.jpg"}]}, "retweeted": false, "coordinates": null, "source": "<a href=\"http://twitter.com\" rel=\"nofollow\">Twitter Web Client</a>", "in_reply_to_screen_name": null, "in_reply_to_user_id": null, "retweet_count": 652, "id_str": "807448196960161792", "favorited": false, "retweeted_status": {"contributors": null, "truncated": false, "text": "Buried deep down this WaPo Secret CIA assessment article they admit they have zero evidence https://t.co/ppaNgmXX9X", "is_quote_status": false, "in_reply_to_status_id": null, "id": 807393274558369792, "favorite_count": 658, "entities": {"symbols": [], "user_mentions": [], "hashtags": [], "urls": [], "media": [{"expanded_url": "https://twitter.com/JackPosobiec/status/807393274558369792/photo/1", "display_url": "pic.twitter.com/ppaNgmXX9X", "url": "https://t.co/ppaNgmXX9X", "media_url_https": "https://pbs.twimg.com/media/CzRv5OFXcAILC2h.jpg", "id_str": "807393262029991938", "sizes": {"small": {"h": 199, "resize": "fit", "w": 680}, "large": {"h": 219, "resize": "fit", "w": 750}, "medium": {"h": 219, "resize": "fit", "w": 750}, "thumb": {"h": 150, "resize": "crop", "w": 150}}, "indices": [92, 115], "type": "photo", "id": 807393262029991938, "media_url": "http://pbs.twimg.com/media/CzRv5OFXcAILC2h.jpg"}]}, "retweeted": false, "coordinates": null, "source": "<a href=\"http://twitter.com/download/iphone\" rel=\"nofollow\">Twitter for iPhone</a>", "in_reply_to_screen_name": null, "in_reply_to_user_id": null, "retweet_count": 652, "id_str": "807393274558369792", "favorited": false, "user": {"follow_request_sent": false, "has_extended_profile": true, "profile_use_background_image": true, "default_profile_image": false, "id": 592730371, "profile_background_image_url_https": "https://pbs.twimg.com/profile_background_images/862971572/fb7aadcfd66ea5e4cad749bf1e4412de.jpeg", "verified": false, "translator_type": "none", "profile_text_color": "333333", "profile_image_url_https": "https://pbs.twimg.com/profile_images/807417528930750465/SLYeon9G_normal.jpg", "profile_sidebar_fill_color": "DDEEF6", "entities": {"description": {"urls": []}}, "followers_count": 58055, "profile_sidebar_border_color": "FFFFFF", "id_str": "592730371", "profile_background_color": "000000", "listed_count": 679, "is_translation_enabled": false, "utc_offset": -18000, "statuses_count": 72647, "description": "Future CEO of @Twitter", "friends_count": 240, "location": "Twitter ", "profile_link_color": "1B95E0", "profile_image_url": "http://pbs.twimg.com/profile_images/807417528930750465/SLYeon9G_normal.jpg", "following": false, "geo_enabled": true, "profile_banner_url": "https://pbs.twimg.com/profile_banners/592730371/1478006640", "profile_background_image_url": "http://pbs.twimg.com/profile_background_images/862971572/fb7aadcfd66ea5e4cad749bf1e4412de.jpeg", "screen_name": "JackPosobiec", "lang": "en", "profile_background_tile": true, "favourites_count": 33739, "name": "Jack Posobiec", "notifications": false, "url": null, "created_at": "Mon May 28 13:31:22 +0000 2012", "contributors_enabled": false, "time_zone": "Eastern Time (US & Canada)", "protected": false, "default_profile": false, "is_translator": false}, "geo": null, "in_reply_to_user_id_str": null, "possibly_sensitive": false, "lang": "en", "created_at": "Sat Dec 10 01:15:31 +0000 2016", "in_reply_to_status_id_str": null, "place": null, "extended_entities": {"media": [{"expanded_url": "https://twitter.com/JackPosobiec/status/807393274558369792/photo/1", "display_url": "pic.twitter.com/ppaNgmXX9X", "url": "https://t.co/ppaNgmXX9X", "media_url_https": "https://pbs.twimg.com/media/CzRv5OFXcAILC2h.jpg", "id_str": "807393262029991938", "sizes": {"small": {"h": 199, "resize": "fit", "w": 680}, "large": {"h": 219, "resize": "fit", "w": 750}, "medium": {"h": 219, "resize": "fit", "w": 750}, "thumb": {"h": 150, "resize": "crop", "w": 150}}, "indices": [92, 115], "type": "photo", "id": 807393262029991938, "media_url": "http://pbs.twimg.com/media/CzRv5OFXcAILC2h.jpg"}]}, "metadata": {"iso_language_code": "en", "result_type": "recent"}}, "user": {"follow_request_sent": false, "has_extended_profile": false, "profile_use_background_image": true, "default_profile_image": false, "id": 4417785753, "profile_background_image_url_https": "https://abs.twimg.com/images/themes/theme1/bg.png", "verified": false, "translator_type": "none", "profile_text_color": "333333", "profile_image_url_https": "https://pbs.twimg.com/profile_images/787456238527348738/kT1YC2mK_normal.jpg", "profile_sidebar_fill_color": "DDEEF6", "entities": {"description": {"urls": []}}, "followers_count": 596, "profile_sidebar_border_color": "C0DEED", "id_str": "4417785753", "profile_background_color": "C0DEED", "listed_count": 2, "is_translation_enabled": false, "utc_offset": -28800, "statuses_count": 6775, "description": "", "friends_count": 271, "location": "", "profile_link_color": "1DA1F2", "profile_image_url": "http://pbs.twimg.com/profile_images/787456238527348738/kT1YC2mK_normal.jpg", "following": false, "geo_enabled": false, "profile_background_image_url": "http://abs.twimg.com/images/themes/theme1/bg.png", "screen_name": "bgail120815", "lang": "en", "profile_background_tile": false, "favourites_count": 33395, "name": "Gail", "notifications": false, "url": null, "created_at": "Tue Dec 08 17:18:27 +0000 2015", "contributors_enabled": false, "time_zone": "Pacific Time (US & Canada)", "protected": false, "default_profile": true, "is_translator": false}, "geo": null, "in_reply_to_user_id_str": null, "possibly_sensitive": false, "lang": "en", "created_at": "Sat Dec 10 04:53:46 +0000 2016", "in_reply_to_status_id_str": null, "place": null, "extended_entities": {"media": [{"source_user_id": 592730371, "source_status_id_str": "807393274558369792", "expanded_url": "https://twitter.com/JackPosobiec/status/807393274558369792/photo/1", "display_url": "pic.twitter.com/ppaNgmXX9X", "url": "https://t.co/ppaNgmXX9X", "media_url_https": "https://pbs.twimg.com/media/CzRv5OFXcAILC2h.jpg", "source_user_id_str": "592730371", "source_status_id": 807393274558369792, "id_str": "807393262029991938", "sizes": {"small": {"h": 199, "resize": "fit", "w": 680}, "large": {"h": 219, "resize": "fit", "w": 750}, "medium": {"h": 219, "resize": "fit", "w": 750}, "thumb": {"h": 150, "resize": "crop", "w": 150}}, "indices": [110, 133], "type": "photo", "id": 807393262029991938, "media_url": "http://pbs.twimg.com/media/CzRv5OFXcAILC2h.jpg"}]}, "metadata": {"iso_language_code": "en", "result_type": "recent"}}