{"is_answered": true, "view_count": 1674, "tags": ["python", "pandas", "matplotlib", "pycharm"], "last_activity_date": 1466819889, "answer_count": 1, "creation_date": 1426282143, "score": 1, "link": "http://stackoverflow.com/questions/29042276/plotting-a-dataframe-pandas-in-pycharm-not-displaying", "accepted_answer_id": 29042575, "owner": {"user_id": 360826, "profile_image": "https://www.gravatar.com/avatar/c59c5507f0ed5004686eef40827682c4?s=128&d=identicon&r=PG", "user_type": "registered", "reputation": 1301, "link": "http://stackoverflow.com/users/360826/jason-m", "accept_rate": 71, "display_name": "jason m"}, "title": "Plotting a dataframe (pandas) in pycharm, not displaying", "last_edit_date": 1466819872, "question_id": 29042276}