{"owner": {"display_name": "xav", "reputation": 461, "profile_image": "https://www.gravatar.com/avatar/0b6fce95508933cb5bf895965239e542?s=128&d=identicon&r=PG", "user_id": 2008527, "user_type": "registered", "accept_rate": 84, "link": "http://stackoverflow.com/users/2008527/xav"}, "link": "http://stackoverflow.com/questions/31855794/whats-the-best-way-to-share-jupyter-notebooks-with-non-programmers", "tags": ["python", "ipython-notebook", "jupyter"], "creation_date": 1438864086, "score": 21, "last_edit_date": 1438865349, "is_answered": true, "view_count": 9585, "last_activity_date": 1477758560, "question_id": 31855794, "accepted_answer_id": 33248969, "answer_count": 5, "title": "What&#39;s the best way to share Jupyter notebooks with non-programmers?"}