{"is_answered": true, "view_count": 217, "tags": ["python", "pandas", "dataframe"], "last_activity_date": 1474109994, "answer_count": 3, "creation_date": 1460398734, "score": 1, "link": "http://stackoverflow.com/questions/36556256/how-do-i-fill-na-values-in-multiple-columns-in-pandas", "accepted_answer_id": 36556382, "owner": {"user_id": 194000, "profile_image": "https://www.gravatar.com/avatar/03e72a161e69eaafe1213344c8568a28?s=128&d=identicon&r=PG", "user_type": "registered", "reputation": 11056, "link": "http://stackoverflow.com/users/194000/richard", "accept_rate": 74, "display_name": "Richard"}, "title": "How do I fill NA values in multiple columns in pandas?", "last_edit_date": 1474109994, "question_id": 36556256}