{"is_answered": true, "view_count": 54, "tags": ["python", "pandas", "dataframe"], "last_activity_date": 1468936240, "answer_count": 2, "creation_date": 1468931843, "score": 0, "link": "http://stackoverflow.com/questions/38458822/pandas-dataframe-adding-rows-to-df-based-on-data-in-df", "accepted_answer_id": 38459239, "owner": {"user_id": 6607832, "profile_image": "https://www.gravatar.com/avatar/d00d3026ba631e87874d45a112871075?s=128&d=identicon&r=PG&f=1", "user_type": "registered", "reputation": 8, "link": "http://stackoverflow.com/users/6607832/j-dav", "display_name": "J_Dav"}, "title": "Pandas DataFrame - Adding rows to df based on data in df", "question_id": 38458822}