{"is_answered": true, "view_count": 37, "tags": ["python", "python-2.7", "pandas"], "last_activity_date": 1470253716, "answer_count": 1, "creation_date": 1470252078, "score": 1, "link": "http://stackoverflow.com/questions/38752010/color-numbers-in-pandas-dataframe", "owner": {"user_id": 6651878, "profile_image": "https://www.gravatar.com/avatar/8c6c195c6f1aee9d22c7f3c476ade825?s=128&d=identicon&r=PG&f=1", "user_type": "registered", "reputation": 6, "link": "http://stackoverflow.com/users/6651878/c-schmidt", "display_name": "C.Schmidt"}, "title": "Color numbers in pandas dataframe", "question_id": 38752010}