{"is_answered": false, "view_count": 55, "tags": ["python", "python-3.x", "pandas", "elementtree"], "last_activity_date": 1470661325, "answer_count": 0, "creation_date": 1470659439, "score": 0, "link": "http://stackoverflow.com/questions/38829291/how-to-loop-through-xml-file-and-save-the-result-into-a-dataframe", "owner": {"user_id": 5547062, "profile_image": "https://www.gravatar.com/avatar/a5d1072aafc215dcbdf50bf71141815a?s=128&d=identicon&r=PG&f=1", "user_type": "registered", "reputation": 6, "link": "http://stackoverflow.com/users/5547062/wdann", "display_name": "Wdann"}, "title": "how to loop through xml file and save the result into a dataframe", "last_edit_date": 1470661325, "question_id": 38829291}