{"is_answered": true, "view_count": 26, "tags": ["python", "pandas", "aggregate"], "last_activity_date": 1471367148, "answer_count": 1, "creation_date": 1471365329, "score": 1, "link": "http://stackoverflow.com/questions/38980138/drop-labels-created-by-aggsum-count", "accepted_answer_id": 38980223, "owner": {"user_id": 668624, "profile_image": "https://i.stack.imgur.com/qMFcJ.jpg?s=128&g=1", "user_type": "registered", "reputation": 1391, "link": "http://stackoverflow.com/users/668624/codingknob", "accept_rate": 87, "display_name": "codingknob"}, "title": "drop labels created by agg([&#39;sum&#39;,&#39;count&#39;])", "last_edit_date": 1471367148, "question_id": 38980138}