{"is_answered": true, "view_count": 42, "tags": ["python", "pandas", "matplotlib"], "last_activity_date": 1471511778, "answer_count": 1, "creation_date": 1471509195, "score": 1, "link": "http://stackoverflow.com/questions/39013425/multiple-stacked-bar-plot-with-pandas", "accepted_answer_id": 39014192, "owner": {"user_id": 1910106, "profile_image": "https://www.gravatar.com/avatar/061b9d2261f16f98f19eff853a4e9496?s=128&d=identicon&r=PG", "user_type": "registered", "reputation": 335, "link": "http://stackoverflow.com/users/1910106/fireboot", "accept_rate": 100, "display_name": "fireboot"}, "title": "Multiple stacked bar plot with pandas", "question_id": 39013425}