{"is_answered": true, "view_count": 24, "tags": ["python", "pandas", "dataframe"], "last_activity_date": 1474225071, "answer_count": 1, "creation_date": 1474224441, "score": 0, "link": "http://stackoverflow.com/questions/39561364/pandas-using-color-in-a-scatter-plot", "accepted_answer_id": 39561457, "owner": {"user_id": 3993270, "profile_image": "https://www.gravatar.com/avatar/1bee661ad7451ff3107ca6954560a06c?s=128&d=identicon&r=PG&f=1", "user_type": "registered", "reputation": 960, "link": "http://stackoverflow.com/users/3993270/edamame", "accept_rate": 61, "display_name": "Edamame"}, "title": "pandas: Using color in a scatter plot", "question_id": 39561364}