{"is_answered": true, "view_count": 45, "tags": ["python", "pandas", "dataframe"], "last_activity_date": 1476674114, "answer_count": 2, "creation_date": 1476666422, "score": 4, "link": "http://stackoverflow.com/questions/40077188/pandas-data-frame-reshaping-values-in-data-frame", "accepted_answer_id": 40077933, "owner": {"user_id": 941759, "profile_image": "https://www.gravatar.com/avatar/552889e3ff579575424f280c57cdc747?s=128&d=identicon&r=PG", "user_type": "registered", "reputation": 160, "link": "http://stackoverflow.com/users/941759/kelly-roper", "accept_rate": 72, "display_name": "Kelly Roper"}, "title": "Pandas - Data Frame - Reshaping Values in Data Frame", "last_edit_date": 1476666918, "question_id": 40077188}