{"last_activity_date": 1477089085, "owner": {"display_name": "Craig Wright", "reputation": 115, "profile_image": "https://www.gravatar.com/avatar/157a6d0e6be302711f281a38bd1938ab?s=128&d=identicon&r=PG", "user_id": 506244, "user_type": "registered", "link": "http://stackoverflow.com/users/506244/craig-wright"}, "is_answered": false, "answer_count": 0, "creation_date": 1477089085, "score": 0, "title": "What file structure to use when deploying a Flask (or any framework) app?", "tags": ["python", "security", "unix", "nginx", "flask"], "view_count": 26, "question_id": 40186300, "link": "http://stackoverflow.com/questions/40186300/what-file-structure-to-use-when-deploying-a-flask-or-any-framework-app"}