{"owner": {"display_name": "Biba", "reputation": 23, "profile_image": "https://www.gravatar.com/avatar/5a2180e1e5f4538b5e4288cce51f47a1?s=128&d=identicon&r=PG&f=1", "user_id": 6643984, "user_type": "registered", "accept_rate": 20, "link": "http://stackoverflow.com/users/6643984/biba"}, "link": "http://stackoverflow.com/questions/40219706/writing-dictionary-to-multiple-columns-in-csv-file-in-python", "tags": ["python"], "creation_date": 1477315644, "score": 1, "last_edit_date": 1477316158, "is_answered": false, "view_count": 43, "last_activity_date": 1477317513, "question_id": 40219706, "answer_count": 1, "title": "Writing dictionary to multiple columns in csv file in python"}