{"owner": {"display_name": "Basj", "reputation": 3177, "profile_image": "https://www.gravatar.com/avatar/da3871bf5450fa726f20557fa3f18f51?s=128&d=identicon&r=PG", "user_id": 1422096, "user_type": "registered", "accept_rate": 65, "link": "http://stackoverflow.com/users/1422096/basj"}, "link": "http://stackoverflow.com/questions/40229175/make-a-dict-persistent", "tags": ["python", "database", "dictionary", "persistence"], "creation_date": 1477351990, "score": 0, "closed_date": 1477352161, "is_answered": false, "view_count": 14, "last_activity_date": 1477351990, "question_id": 40229175, "closed_reason": "duplicate", "answer_count": 0, "title": "Make a dict persistent"}