{"owner": {"display_name": "Aboogie", "reputation": 90, "profile_image": "https://www.gravatar.com/avatar/8c773d1ecc8e3999474b5c6f152c2047?s=128&d=identicon&r=PG&f=1", "user_id": 5415499, "user_type": "registered", "accept_rate": 57, "link": "http://stackoverflow.com/users/5415499/aboogie"}, "link": "http://stackoverflow.com/questions/40221258/tkinter-and-multiple-threads", "tags": ["python", "multithreading", "tkinter", "udp", "python-multithreading"], "creation_date": 1477320161, "score": 0, "last_edit_date": 1477320892, "is_answered": true, "view_count": 28, "last_activity_date": 1477320895, "question_id": 40221258, "accepted_answer_id": 40221456, "answer_count": 1, "title": "tkinter and multiple threads"}