{"owner": {"display_name": "mgruber", "reputation": 25, "profile_image": "https://www.gravatar.com/avatar/976a2280e5fe2a217e23108d2c7ee17d?s=128&d=identicon&r=PG&f=1", "user_id": 6359622, "user_type": "registered", "accept_rate": 67, "link": "http://stackoverflow.com/users/6359622/mgruber"}, "link": "http://stackoverflow.com/questions/40255374/splitting-strings-of-a-list-on-a-separator-if-it-appears", "tags": ["python", "list", "loops", "unicode"], "creation_date": 1477464103, "score": 1, "last_edit_date": 1477464407, "is_answered": true, "view_count": 25, "last_activity_date": 1477464736, "question_id": 40255374, "accepted_answer_id": 40255448, "answer_count": 1, "title": "Splitting strings of a list on a separator if it appears"}