{"is_answered": true, "view_count": 40, "tags": ["python", "pandas"], "last_activity_date": 1477444149, "answer_count": 1, "creation_date": 1477442639, "score": 3, "link": "http://stackoverflow.com/questions/40251948/stop-pandas-from-converting-int-to-float", "accepted_answer_id": 40252138, "owner": {"user_id": 2570465, "profile_image": "https://www.gravatar.com/avatar/14da57290208c66d0846cfab5fbe3577?s=128&d=identicon&r=PG", "user_type": "registered", "reputation": 812, "link": "http://stackoverflow.com/users/2570465/user2570465", "accept_rate": 91, "display_name": "user2570465"}, "title": "Stop Pandas from Converting Int to Float", "question_id": 40251948}