{"last_activity_date": 1477442185, "owner": {"display_name": "BPL", "reputation": 3183, "profile_image": "https://www.gravatar.com/avatar/2ae2812de72bafa695a146317d4b154f?s=128&d=identicon&r=PG&f=1", "user_id": 3809375, "user_type": "registered", "accept_rate": 77, "link": "http://stackoverflow.com/users/3809375/bpl"}, "is_answered": false, "answer_count": 0, "creation_date": 1477442185, "score": 0, "title": "is it possible to modify PYTHONPATH on a Sublime-Project generated by CMake?", "tags": ["python", "windows", "cmake", "sublimetext3", "swig"], "view_count": 11, "question_id": 40251881, "link": "http://stackoverflow.com/questions/40251881/is-it-possible-to-modify-pythonpath-on-a-sublime-project-generated-by-cmake"}