{"last_activity_date": 1477762730, "owner": {"display_name": "Tanzil Khan", "reputation": 16, "profile_image": "https://i.stack.imgur.com/obOnv.jpg?s=128&g=1", "user_id": 3666181, "user_type": "registered", "accept_rate": 75, "link": "http://stackoverflow.com/users/3666181/tanzil-khan"}, "is_answered": false, "answer_count": 0, "creation_date": 1477762730, "score": -1, "title": "How to remove google sign in from google map", "tags": ["python", "google-maps", "iframe", "odoo-8"], "view_count": 26, "question_id": 40321818, "link": "http://stackoverflow.com/questions/40321818/how-to-remove-google-sign-in-from-google-map"}