{"Plot": "There are more than 40,000 men and women locked up in North Carolina prisons. Of these inmates, 98 percent will eventually re-enter society. LeJhoyn Holland and Bill Rasor were released ...", "Rated": "N/A", "Response": "True", "Language": "English", "Title": "Against the Tide", "Country": "USA, UK", "Writer": "N/A", "Metascore": "N/A", "imdbRating": "N/A", "Director": "Alan Julich", "Released": "02 Mar 2011", "Actors": "Lejhoyn Holland, Jean-Michel Margot, Bill Rasor", "Year": "2011", "Genre": "Documentary, Short, Drama", "Awards": "N/A", "Runtime": "25 min", "Type": "movie", "Poster": "N/A", "imdbVotes": "N/A", "imdbID": "tt1964470"}